filesreader.py
filesreader-0.1.2.dist-info/LICENSE
filesreader-0.1.2.dist-info/METADATA
filesreader-0.1.2.dist-info/WHEEL
filesreader-0.1.2.dist-info/RECORD
